reugin/__init__.py
reugin/methods.py
reugin/mounts.py
reugin/multipartformdata.py
reugin/request.py
reugin/response.py
reugin/route_match.py
reugin/server.py
reugin/unjustpython.py
reugin/connectors/__init__.py
reugin/connectors/base.py
reugin/connectors/http.py
reugin/connectors/rpc.py
reugin/connectors/ws.py
reugin/rhtml/__init__.py
reugin/rhtml/misc.py
reugin/rhtml/tags.py
reugin-0.2.8.dist-info/LICENSE
reugin-0.2.8.dist-info/METADATA
reugin-0.2.8.dist-info/WHEEL
reugin-0.2.8.dist-info/top_level.txt
reugin-0.2.8.dist-info/RECORD
