Metadata-Version: 2.1
Name: reugin
Version: 0.2.8
Summary: Reugin, an ASGI framework
Home-page: https://github.com/geckwwo/reugin
Author: geckwwo
Project-URL: Bug Tracker, https://github.com/geckwwo/reugin/issues
Project-URL: repository, https://github.com/geckwwo/reugin
Classifier: Programming Language :: Python :: 3
Classifier: License :: OSI Approved :: BSD License
Classifier: Operating System :: OS Independent
Requires-Python: >=3.10
License-File: LICENSE
